README.md
scripts/__init__.py
scripts/fuzzy_phrase_matcher.py
scripts/utils.py
phuzzymatcher-0.0.1.dist-info/LICENSE
phuzzymatcher-0.0.1.dist-info/WHEEL
phuzzymatcher-0.0.1.dist-info/METADATA
phuzzymatcher-0.0.1.dist-info/RECORD
